roku_scanner/__init__.py
roku_scanner/__main__.py
roku_scanner/custom_types.py
roku_scanner/roku.py
roku_scanner/scanner.py
roku_scanner-1.0.4.dist-info/LICENSE.md
roku_scanner-1.0.4.dist-info/METADATA
roku_scanner-1.0.4.dist-info/WHEEL
roku_scanner-1.0.4.dist-info/entry_points.txt
roku_scanner-1.0.4.dist-info/top_level.txt
roku_scanner-1.0.4.dist-info/RECORD
