Metadata-Version: 2.1
Name: roku-scanner
Version: 1.0.4
Summary: Scans LAN for any Roku devices and fetches device, app, active-app, and player information.
Home-page: https://github.com/CCecilia/Roku-Scanner
Author: Christian Cecilia
Author-email: christian.cecilia1@gmail.com
License: MIT
Platform: UNKNOWN
Classifier: License :: OSI Approved :: MIT License
Classifier: Programming Language :: Python :: 3
Classifier: Programming Language :: Python :: 3.8
Requires-Dist: requests
Requires-Dist: tqdm
Requires-Dist: xmltodict
